pyxdsm/XDSM.py
pyxdsm/__init__.py
pyxdsm/diagram_styles.tex
pyxdsm/matrix_eqn.py
pyXDSM-2.3.0.dist-info/LICENSE.txt
pyXDSM-2.3.0.dist-info/METADATA
pyXDSM-2.3.0.dist-info/WHEEL
pyXDSM-2.3.0.dist-info/top_level.txt
pyXDSM-2.3.0.dist-info/RECORD
