Metadata-Version: 2.1
Name: pyXDSM
Version: 2.3.0
Summary: Python script to generate PDF XDSM diagrams using TikZ and LaTeX
Home-page: https://github.com/mdolab/pyXDSM
Author: 
Author-email: 
License: Apache License Version 2.0
Keywords: optimization multidisciplinary multi-disciplinary analysis n2 xdsm
Platform: UNKNOWN
Classifier: Operating System :: OS Independent
Classifier: Programming Language :: Python
Classifier: Topic :: Scientific/Engineering
Classifier: Programming Language :: Python
Classifier: Programming Language :: Python :: 3.6
Classifier: Programming Language :: Python :: 3.7
Classifier: Programming Language :: Python :: 3.8
Requires-Python: >=3
License-File: LICENSE.txt
Requires-Dist: numpy (>=1.16)
